zaber_motion_bindings_linux/__init__.py
zaber_motion_bindings_linux/bindings.py
zaber_motion_bindings_linux/version.py
zaber_motion_bindings_linux/zaber-motion-lib-linux-386.so
zaber_motion_bindings_linux/zaber-motion-lib-linux-amd64.so
zaber_motion_bindings_linux/zaber-motion-lib-linux-arm.so
zaber_motion_bindings_linux/zaber-motion-lib-linux-arm64.so
zaber_motion_bindings_linux-5.1.1.dist-info/LICENSE.txt
zaber_motion_bindings_linux-5.1.1.dist-info/METADATA
zaber_motion_bindings_linux-5.1.1.dist-info/WHEEL
zaber_motion_bindings_linux-5.1.1.dist-info/top_level.txt
zaber_motion_bindings_linux-5.1.1.dist-info/RECORD
